openalgo/__init__.py
openalgo/account.py
openalgo/base.py
openalgo/data.py
openalgo/feed.py
openalgo/numba_shim.py
openalgo/options.py
openalgo/orders.py
openalgo/strategy.py
openalgo/telegram.py
openalgo/utilities.py
openalgo/indicators/__init__.py
openalgo/indicators/base.py
openalgo/indicators/hybrid.py
openalgo/indicators/momentum.py
openalgo/indicators/oscillators.py
openalgo/indicators/statistics.py
openalgo/indicators/trend.py
openalgo/indicators/utils.py
openalgo/indicators/volatility.py
openalgo/indicators/volume.py
openalgo-1.0.44.dist-info/licenses/LICENSE
openalgo-1.0.44.dist-info/METADATA
openalgo-1.0.44.dist-info/WHEEL
openalgo-1.0.44.dist-info/top_level.txt
openalgo-1.0.44.dist-info/RECORD
