Metadata-Version: 2.4
Name: openalgo
Version: 1.0.44
Summary: A Python library for interacting with OpenAlgo's trading APIs with high-performance technical indicators
Home-page: https://openalgo.in
Author: Rajandran R
Author-email: rajandran@openalgo.in
Project-URL: Documentation, https://docs.openalgo.in
Project-URL: Source, https://github.com/openalgo/openalgo-python
Project-URL: Tracker, https://github.com/openalgo/openalgo-python/issues
Keywords: trading,algorithmic-trading,finance,websocket,market-data,real-time,stock-market,api-wrapper,openalgo,market-data,trading-api,stock-trading,technical-analysis,indicators,rsi,macd,sma,ema,bollinger-bands,supertrend,atr,volume-analysis
Classifier: Development Status :: 5 - Production/Stable
Classifier: Intended Audience :: Developers
Classifier: Intended Audience :: Financial and Insurance Industry
Classifier: License :: OSI Approved :: MIT License
Classifier: Operating System :: OS Independent
Classifier: Programming Language :: Python :: 3
Classifier: Programming Language :: Python :: 3.7
Classifier: Programming Language :: Python :: 3.8
Classifier: Programming Language :: Python :: 3.9
Classifier: Programming Language :: Python :: 3.10
Classifier: Programming Language :: Python :: 3.11
Classifier: Programming Language :: Python :: 3.12
Classifier: Programming Language :: Python :: 3.13
Classifier: Programming Language :: Python :: 3.14
Classifier: Topic :: Office/Business :: Financial :: Investment
Classifier: Topic :: Software Development :: Libraries :: Python Modules
Requires-Python: >=3.7
License-File: LICENSE
Requires-Dist: httpx>=0.23.0
Requires-Dist: pandas>=1.2.0
Requires-Dist: websocket-client>=1.8.0
Requires-Dist: numpy>=2.0.0
Requires-Dist: numba>=0.63.0b1
Dynamic: author
Dynamic: author-email
Dynamic: classifier
Dynamic: description
Dynamic: description-content-type
Dynamic: home-page
Dynamic: keywords
Dynamic: license-file
Dynamic: project-url
Dynamic: requires-dist
Dynamic: requires-python
Dynamic: summary
